.gitignore
CHANGES.txt
CONTRIBUTORS.txt
MANIFEST.in
README.rst
bootstrap-buildout.py
buildout.cfg
setup.py
docs/LICENSE.GPL
docs/LICENSE.txt
src/koslab/__init__.py
src/koslab.recipe.zipapp.egg-info/PKG-INFO
src/koslab.recipe.zipapp.egg-info/SOURCES.txt
src/koslab.recipe.zipapp.egg-info/dependency_links.txt
src/koslab.recipe.zipapp.egg-info/entry_points.txt
src/koslab.recipe.zipapp.egg-info/namespace_packages.txt
src/koslab.recipe.zipapp.egg-info/not-zip-safe
src/koslab.recipe.zipapp.egg-info/requires.txt
src/koslab.recipe.zipapp.egg-info/top_level.txt
src/koslab/recipe/__init__.py
src/koslab/recipe/zipapp/__init__.py
src/koslab/recipe/zipapp/builder.py
src/koslab/recipe/zipapp/buildout_recipe.py