Metadata-Version: 1.1
Name: koslab.recipe.zipapp
Version: 1.0
Summary: Python ZipApp Packager
Home-page: http://github.com/koslab/koslab.recipe.zipapp/
Author: Izhar Firdaus
Author-email: izhar@kagesenshi.org
License: gpl
Keywords: buildout zipapp
Platform: UNKNOWN
Classifier: Programming Language :: Python
